{"nodes": [{"id": "svg_i_gap_igap_logo", "label": "iGap Logo", "file_type": "image", "source_file": "public/assets/svg/I-GAP.svg", "source_location": null, "source_url": null, "captured_at": null, "author": null, "contributor": null, "description": "SVG logo for iGap, an Iranian messaging application. The logo depicts a spiral or swirl shape composed of layered green-toned paths (ranging from light #edf6e5 to dark #4eb95b), forming a recognizable brand mark with a white center. The design uses multiple overlapping curved segments to create depth and a circular/vortex aesthetic on a 500x500 viewBox.", "properties": {"brand": "iGap", "brand_type": "Iranian messaging app", "color_palette": ["#add251", "#89c756", "#c7e09e", "#dbeccb", "#6bbf59", "#4eb95b", "#ffffff"], "viewBox": "0 0 500 500", "shape": "spiral/swirl", "purpose": "brand_logo"}}], "edges": [], "hyperedges": []}