{"nodes": [{"id": "docs_pagebuilder_page_builder", "label": "Page Builder Architecture", "file_type": "document", "source_file": "docs/PAGE-BULDER.md", "source_location": null, "source_url": null, "captured_at": null, "author": null, "contributor": null}, {"id": "docs_pagebuilder_page_block", "label": "PageBlock (embedded block snapshot)", "file_type": "concept", "source_file": "docs/PAGE-BULDER.md", "source_location": null, "source_url": null, "captured_at": null, "author": null, "contributor": null}, {"id": "docs_pagebuilder_block_element", "label": "BlockElement (label, style, allowedStyleKeys)", "file_type": "concept", "source_file": "docs/PAGE-BULDER.md", "source_location": null, "source_url": null, "captured_at": null, "author": null, "contributor": null}, {"id": "docs_pagebuilder_editable_style_map", "label": "EditableStyleMap (color, backgroundColor, fontSize, etc.)", "file_type": "concept", "source_file": "docs/PAGE-BULDER.md", "source_location": null, "source_url": null, "captured_at": null, "author": null, "contributor": null}, {"id": "docs_pagebuilder_block_registry", "label": "blockRegistry (block type registry)", "file_type": "concept", "source_file": "docs/PAGE-BULDER.md", "source_location": null, "source_url": null, "captured_at": null, "author": null, "contributor": null}, {"id": "docs_pagebuilder_simple_page_builder", "label": "SimplePageBuilder (editor orchestrator)", "file_type": "concept", "source_file": "docs/PAGE-BULDER.md", "source_location": null, "source_url": null, "captured_at": null, "author": null, "contributor": null}, {"id": "docs_pagebuilder_dynamic_island", "label": "DynamicIslandPanel (floating edit panel)", "file_type": "concept", "source_file": "docs/PAGE-BULDER.md", "source_location": null, "source_url": null, "captured_at": null, "author": null, "contributor": null}, {"id": "docs_pagebuilder_phone_preview", "label": "PhonePreviewModal", "file_type": "concept", "source_file": "docs/PAGE-BULDER.md", "source_location": null, "source_url": null, "captured_at": null, "author": null, "contributor": null}, {"id": "docs_pagebuilder_dnd_kit", "label": "dnd-kit Drag and Drop", "file_type": "concept", "source_file": "docs/PAGE-BULDER.md", "source_location": null, "source_url": null, "captured_at": null, "author": null, "contributor": null}, {"id": "docs_pagebuilder_block_snapshot_rationale", "label": "Store Full Block Snapshot in Page.blocks (no master-block dependency after creation)", "file_type": "rationale", "source_file": "docs/PAGE-BULDER.md", "source_location": null, "source_url": null, "captured_at": null, "author": null, "contributor": null}, {"id": "docs_pagebuilder_repeater_field", "label": "RepeaterField for Array Data", "file_type": "concept", "source_file": "docs/PAGE-BULDER.md", "source_location": null, "source_url": null, "captured_at": null, "author": null, "contributor": null}, {"id": "docs_pagebuilder_responsive_value", "label": "ResponsiveValue (mobile/tablet/desktop)", "file_type": "concept", "source_file": "docs/PAGE-BULDER.md", "source_location": null, "source_url": null, "captured_at": null, "author": null, "contributor": null}], "edges": [{"source": "docs_pagebuilder_page_builder", "target": "docs_pagebuilder_page_block", "relation": "references", "confidence": "EXTRACTED", "confidence_score": 1.0, "source_file": "docs/PAGE-BULDER.md", "source_location": null, "weight": 1.0}, {"source": "docs_pagebuilder_page_builder", "target": "docs_pagebuilder_block_element", "relation": "references", "confidence": "EXTRACTED", "confidence_score": 1.0, "source_file": "docs/PAGE-BULDER.md", "source_location": null, "weight": 1.0}, {"source": "docs_pagebuilder_page_builder", "target": "docs_pagebuilder_editable_style_map", "relation": "references", "confidence": "EXTRACTED", "confidence_score": 1.0, "source_file": "docs/PAGE-BULDER.md", "source_location": null, "weight": 1.0}, {"source": "docs_pagebuilder_page_builder", "target": "docs_pagebuilder_block_registry", "relation": "references", "confidence": "EXTRACTED", "confidence_score": 1.0, "source_file": "docs/PAGE-BULDER.md", "source_location": null, "weight": 1.0}, {"source": "docs_pagebuilder_page_builder", "target": "docs_pagebuilder_simple_page_builder", "relation": "references", "confidence": "EXTRACTED", "confidence_score": 1.0, "source_file": "docs/PAGE-BULDER.md", "source_location": null, "weight": 1.0}, {"source": "docs_pagebuilder_page_builder", "target": "docs_pagebuilder_dynamic_island", "relation": "references", "confidence": "EXTRACTED", "confidence_score": 1.0, "source_file": "docs/PAGE-BULDER.md", "source_location": null, "weight": 1.0}, {"source": "docs_pagebuilder_page_builder", "target": "docs_pagebuilder_phone_preview", "relation": "references", "confidence": "EXTRACTED", "confidence_score": 1.0, "source_file": "docs/PAGE-BULDER.md", "source_location": null, "weight": 1.0}, {"source": "docs_pagebuilder_page_builder", "target": "docs_pagebuilder_dnd_kit", "relation": "references", "confidence": "EXTRACTED", "confidence_score": 1.0, "source_file": "docs/PAGE-BULDER.md", "source_location": null, "weight": 1.0}, {"source": "docs_pagebuilder_page_builder", "target": "docs_pagebuilder_repeater_field", "relation": "references", "confidence": "EXTRACTED", "confidence_score": 1.0, "source_file": "docs/PAGE-BULDER.md", "source_location": null, "weight": 1.0}, {"source": "docs_pagebuilder_page_builder", "target": "docs_pagebuilder_responsive_value", "relation": "references", "confidence": "EXTRACTED", "confidence_score": 1.0, "source_file": "docs/PAGE-BULDER.md", "source_location": null, "weight": 1.0}, {"source": "docs_pagebuilder_block_element", "target": "docs_pagebuilder_editable_style_map", "relation": "shares_data_with", "confidence": "EXTRACTED", "confidence_score": 1.0, "source_file": "docs/PAGE-BULDER.md", "source_location": "BlockElement.style is EditableStyleMap", "weight": 1.0}, {"source": "docs_pagebuilder_editable_style_map", "target": "docs_pagebuilder_responsive_value", "relation": "shares_data_with", "confidence": "EXTRACTED", "confidence_score": 1.0, "source_file": "docs/PAGE-BULDER.md", "source_location": "EditableStyleMap uses ResponsiveValue<T>", "weight": 1.0}, {"source": "docs_pagebuilder_page_block", "target": "docs_pagebuilder_block_element", "relation": "shares_data_with", "confidence": "EXTRACTED", "confidence_score": 1.0, "source_file": "docs/PAGE-BULDER.md", "source_location": "PageBlock.elements: Record<string, BlockElement>", "weight": 1.0}, {"source": "docs_pagebuilder_block_registry", "target": "docs_pagebuilder_simple_page_builder", "relation": "references", "confidence": "EXTRACTED", "confidence_score": 1.0, "source_file": "docs/PAGE-BULDER.md", "source_location": "SimplePageBuilder uses blockRegistry to add blocks", "weight": 1.0}, {"source": "docs_pagebuilder_simple_page_builder", "target": "docs_pagebuilder_dynamic_island", "relation": "references", "confidence": "EXTRACTED", "confidence_score": 1.0, "source_file": "docs/PAGE-BULDER.md", "source_location": "SimplePageBuilder renders DynamicIslandPanel", "weight": 1.0}, {"source": "docs_pagebuilder_simple_page_builder", "target": "docs_pagebuilder_dnd_kit", "relation": "references", "confidence": "EXTRACTED", "confidence_score": 1.0, "source_file": "docs/PAGE-BULDER.md", "source_location": "drag and drop in SimplePageBuilder", "weight": 1.0}, {"source": "docs_pagebuilder_block_snapshot_rationale", "target": "docs_pagebuilder_page_block", "relation": "rationale_for", "confidence": "EXTRACTED", "confidence_score": 1.0, "source_file": "docs/PAGE-BULDER.md", "source_location": "Section 17-18", "weight": 1.0}, {"source": "docs_pagebuilder_page_block", "target": "models_page_model", "relation": "shares_data_with", "confidence": "EXTRACTED", "confidence_score": 1.0, "source_file": "docs/PAGE-BULDER.md", "source_location": "Page.blocks contains PageBlock[]", "weight": 1.0}, {"source": "docs_pagebuilder_simple_page_builder", "target": "docs_pagebulderstructure_page_builder_orchestrator", "relation": "semantically_similar_to", "confidence": "INFERRED", "confidence_score": 0.95, "source_file": "docs/PAGE-BULDER.md", "source_location": null, "weight": 1.0}, {"source": "docs_pagebuilder_dynamic_island", "target": "docs_pagebulderstructure_dynamic_island_panel", "relation": "semantically_similar_to", "confidence": "INFERRED", "confidence_score": 0.95, "source_file": "docs/PAGE-BULDER.md", "source_location": null, "weight": 1.0}], "hyperedges": []}